LICENSE
MANIFEST.in
README.md
setup.cfg
setup.py
versioneer.py
xrt_spec_dl/__init__.py
xrt_spec_dl/_version.py
xrt_spec_dl/lightcurve.py
xrt_spec_dl/xrt_spec_dl.py
xrt_spec_dl.egg-info/PKG-INFO
xrt_spec_dl.egg-info/SOURCES.txt
xrt_spec_dl.egg-info/dependency_links.txt
xrt_spec_dl.egg-info/requires.txt
xrt_spec_dl.egg-info/top_level.txt
xrt_spec_dl/data/__init__.py
xrt_spec_dl/io/__init__.py
xrt_spec_dl/utils/__init__.py
xrt_spec_dl/utils/file_utils.py
xrt_spec_dl/utils/logging.py
xrt_spec_dl/utils/package_data.py