Metadata-Version: 2.1
Name: xrt-spec-dl
Version: 0.2.0
Summary: simple tool to download XRT time slices
Home-page: https://github.com/grburgess/xrt_spec_dl
Author: J. Michael Burgess
Author-email: jburgess@mpe.mpg.de
License: GPL-3+
Project-URL: Bug Tracker, https://github.com/grburgess/xrt_spec_dl/issues
Project-URL: Source Code, https://github.com/grburgess/xrt_spec_dl
Platform: UNKNOWN
Classifier: Development Status :: 2 - Pre-Alpha
Classifier: Environment :: Console
Classifier: Intended Audience :: Science/Research
Classifier: License :: OSI Approved :: GNU General Public License v2 or later (GPLv2+)
Classifier: Operating System :: POSIX
Classifier: Programming Language :: Python :: 3.5
Classifier: Programming Language :: Python :: 3.6
Classifier: Programming Language :: Python :: 3.7
Classifier: Programming Language :: Python :: 3.8
Classifier: Topic :: Scientific/Engineering :: Physics
